uart_tx.sv
`default_nettype none
`ifndef UART_TX_SV
`define UART_TX_SV

module uart_tx (
    input clk,
    input uart_clk_en,
    input [7:0] data,
    input start_tx,
    input rst,
    output reg uart_out,
    output reg ready

);
    

//State definitions and reset

reg [3:0] state;
reg [3:0] next_state;

localparam [3:0] UART_IDLE = 0;
localparam [3:0] UART_START_BIT = 1;
localparam [3:0] UART_START_TX = 2;
localparam [3:0] UART_STOP_BIT = 10;

reg [7:0] buffer;


initial begin
    buffer = 0;
    state = UART_IDLE;
    next_state = UART_IDLE;
    uart_out = 1;
end


always @(posedge clk) begin
    if(uart_clk_en) begin
        state <= next_state;
    end
end

always @(posedge clk) begin
    if ( state == UART_IDLE ) begin
        if (start_tx) begin
            buffer <= data;
            next_state <= UART_START_BIT;
            ready <= 0;
        end
        else begin
            ready <= 1;
            uart_out <= 1;
        end
    end
end

always @(posedge clk) begin
    if (state == UART_START_BIT) begin
        uart_out <= 0;
        next_state <= UART_START_TX;
    end else if (state >= UART_START_TX && state < UART_STOP_BIT) begin
        uart_out <= buffer[state-2];
        next_state <= state + 1;
    end else if (state == UART_STOP_BIT) begin
        uart_out <= 1;
        next_state <= UART_IDLE;
    end else if (state > UART_STOP_BIT) begin
        next_state <= UART_IDLE;
    end
end

endmodule



`endif

tb_uart.sv
`include "uart_tx.sv"
`default_nettype none
`timescale 1 ns/10 ps

module tb;

    reg clk;
    wire out_test;
    reg uart_clk;
    reg [2:0] clk_div_reg;
    reg tx_interval_timer;
    reg [2:0] tx_interval_timer_ctr;


    uart_tx u_uart_tx(
    	.clk         (clk         ),
        .uart_clk_en (uart_clk ),
        .data        (8'h41        ),
        .start_tx    (tx_interval_timer    ),
        .rst         (0         ),
        .uart_out    (out_test    ),
        .ready ()
    );
    

    initial begin
        clk = 0;
        clk_div_reg = 0;
        uart_clk = 0;
        tx_interval_timer_ctr = 0;
        tx_interval_timer = 0;
        $dumpfile ("test.vcd");
        $dumpvars;
    end
/*
    always @(posedge clk) begin
        tx_interval_timer_ctr = tx_interval_timer_ctr + 1;
        if (tx_interval_timer_ctr == 3) begin
            tx_interval_timer = 1;
        end else if (tx_interval_timer_ctr == 4) begin
            tx_interval_timer = 0;
            tx_interval_timer_ctr = 0;
        end
    end
*/
    always @(posedge clk) begin
        clk_div_reg = clk_div_reg + 1;
        if (clk_div_reg == 2) begin
            uart_clk = 1;
        end else if (clk_div_reg == 3) begin
            uart_clk = 0;
            clk_div_reg = 0;
        end
    end

    always
        #1 clk = ~clk;

    initial begin
        #9 tx_interval_timer = 1;
        #2 tx_interval_timer = 0;
        #120 $finish;
    end

endmodule

test.vcd
$date
	Wed Jun  3 21:59:24 2020
$end
$version
	Icarus Verilog
$end
$timescale
	10ps
$end
$scope module tb $end
$var wire 1 ! out_test $end
$var reg 1 " clk $end
$var reg 3 # clk_div_reg [2:0] $end
$var reg 1 $ tx_interval_timer $end
$var reg 3 % tx_interval_timer_ctr [2:0] $end
$var reg 1 & uart_clk $end
$scope module u_uart_tx $end
$var wire 1 " clk $end
$var wire 8 ' data [7:0] $end
$var wire 1 ( rst $end
$var wire 1 $ start_tx $end
$var wire 1 & uart_clk_en $end
$var reg 8 ) buffer [7:0] $end
$var reg 4 * next_state [3:0] $end
$var reg 1 + ready $end
$var reg 4 , state [3:0] $end
$var reg 1 ! uart_out $end
$upscope $end
$upscope $end
$enddefinitions $end
#0
$dumpvars
b0 ,
x+
b0 *
b0 )
0(
b1000001 '
0&
b0 %
0$
b0 #
0"
1!
$end
#100
1+
b1 #
1"
#200
0"
#300
1&
b10 #
1"
#400
0"
#500
0&
b0 #
1"
#600
0"
#700
b1 #
1"
#800
0"
#900
0+
b1 *
b1000001 )
1&
b10 #
1"
1$
#1000
0"
#1100
1+
b1 ,
0&
b0 #
1"
0$
#1200
0"
#1300
b10 *
0!
b1 #
1"
#1400
0"
#1500
1&
b10 #
1"
#1600
0"
#1700
0&
b0 #
1"
#1800
0"
#1900
b1 #
1"
#2000
0"
#2100
b10 ,
1&
b10 #
1"
#2200
0"
#2300
b11 *
1!
0&
b0 #
1"
#2400
0"
#2500
b1 #
1"
#2600
0"
#2700
1&
b10 #
1"
#2800
0"
#2900
0&
b0 #
1"
#3000
0"
#3100
b1 #
1"
#3200
0"
#3300
b11 ,
1&
b10 #
1"
#3400
0"
#3500
b100 *
0!
0&
b0 #
1"
#3600
0"
#3700
b1 #
1"
#3800
0"
#3900
1&
b10 #
1"
#4000
0"
#4100
0&
b0 #
1"
#4200
0"
#4300
b1 #
1"
#4400
0"
#4500
b100 ,
1&
b10 #
1"
#4600
0"
#4700
b101 *
0&
b0 #
1"
#4800
0"
#4900
b1 #
1"
#5000
0"
#5100
1&
b10 #
1"
#5200
0"
#5300
0&
b0 #
1"
#5400
0"
#5500
b1 #
1"
#5600
0"
#5700
b101 ,
1&
b10 #
1"
#5800
0"
#5900
b110 *
0&
b0 #
1"
#6000
0"
#6100
b1 #
1"
#6200
0"
#6300
1&
b10 #
1"
#6400
0"
#6500
0&
b0 #
1"
#6600
0"
#6700
b1 #
1"
#6800
0"
#6900
b110 ,
1&
b10 #
1"
#7000
0"
#7100
b111 *
0&
b0 #
1"
#7200
0"
#7300
b1 #
1"
#7400
0"
#7500
1&
b10 #
1"
#7600
0"
#7700
0&
b0 #
1"
#7800
0"
#7900
b1 #
1"
#8000
0"
#8100
b111 ,
1&
b10 #
1"
#8200
0"
#8300
b1000 *
0&
b0 #
1"
#8400
0"
#8500
b1 #
1"
#8600
0"
#8700
1&
b10 #
1"
#8800
0"
#8900
0&
b0 #
1"
#9000
0"
#9100
b1 #
1"
#9200
0"
#9300
b1000 ,
1&
b10 #
1"
#9400
0"
#9500
b1001 *
1!
0&
b0 #
1"
#9600
0"
#9700
b1 #
1"
#9800
0"
#9900
1&
b10 #
1"
#10000
0"
#10100
0&
b0 #
1"
#10200
0"
#10300
b1 #
1"
#10400
0"
#10500
b1001 ,
1&
b10 #
1"
#10600
0"
#10700
b1010 *
0!
0&
b0 #
1"
#10800
0"
#10900
b1 #
1"
#11000
0"
#11100
1&
b10 #
1"
#11200
0"
#11300
0&
b0 #
1"
#11400
0"
#11500
b1 #
1"
#11600
0"
#11700
b1010 ,
1&
b10 #
1"
#11800
0"
#11900
b0 *
1!
0&
b0 #
1"
#12000
0"
#12100
b1 #
1"
#12200
0"
#12300
1&
b10 #
1"
#12400
0"
#12500
0&
b0 #
1"
#12600
0"
#12700
b1 #
1"
#12800
0"
#12900
b0 ,
1&
b10 #
1"
#13000
0"
#13100
0&
b0 #
1"
